 [{
  "name": "Apple",
  "titleColor": "black",
  "image": "apple",
  "sound": "apple"
  },
  {
  "name": "Orange",
  "titleColor": "black",
  "image": "orange",
  "sound": "orange"
  },
  {
  "name": "Peach",
  "titleColor": "black",
  "image": "peach",
  "sound": "peach"
  },
  {
  "name": "Grapes",
  "titleColor": "black",
  "image": "grapes",
  "sound": "grapes"
  },
  {
  "name": "Watermelon",
  "titleColor": "black",
  "image": "watermelon",
  "sound": "watermelon"
  },
  {
  "name": "Papaya",
  "titleColor": "black",
  "image": "papaya",
  "sound": "papaya"
  },
  {
  "name": "Pear",
  "titleColor": "black",
  "image": "pear",
  "sound": "pear"
  },
  {
  "name": "Banana",
  "titleColor": "black",
  "image": "banana",
  "sound": "banana"
  },
  {
  "name": "Kiwi",
  "titleColor": "black",
  "image": "kiwi",
  "sound": "kiwi"
  },
  {
  "name": "Coconut",
  "titleColor": "black",
  "image": "coconut",
  "sound": "coconut"
  }
  ]
